toconline/__init__.py
toconline/admin.py
toconline/apps.py
toconline/migrations/0001_initial.py
toconline/migrations/__init__.py
toconline/models.py
toconline/resources.py
toconline/services.py
django_toconline-1.0.2.dist-info/LICENSE
django_toconline-1.0.2.dist-info/METADATA
django_toconline-1.0.2.dist-info/WHEEL
django_toconline-1.0.2.dist-info/RECORD
